bana/__init__.py
bana/_iterator.py
bana/_pattern.py
bana/OpenMaya/MDagPath.py
bana/OpenMaya/MFnBase.py
bana/OpenMaya/MFnDagNode.py
bana/OpenMaya/MFnDependencyNode.py
bana/OpenMaya/MFnTransform.py
bana/OpenMaya/MGlobal.py
bana/OpenMaya/MMatrix.py
bana/OpenMaya/MObject.py
bana/OpenMaya/MPoint.py
bana/OpenMaya/MQuaternion.py
bana/OpenMaya/MTransformationMatrix.py
bana/OpenMaya/MVector.py
bana/OpenMaya/__init__.py
bana/OpenMayaAnim/__init__.py
bana/OpenMayaFX/__init__.py
bana/OpenMayaRender/__init__.py
bana/OpenMayaUI/__init__.py
bana-0.1.0.dist-info/DESCRIPTION.rst
bana-0.1.0.dist-info/LICENSE.txt
bana-0.1.0.dist-info/METADATA
bana-0.1.0.dist-info/RECORD
bana-0.1.0.dist-info/WHEEL
bana-0.1.0.dist-info/metadata.json
bana-0.1.0.dist-info/top_level.txt
