Metadata-Version: 2.0
Name: bana
Version: 0.1.0
Summary: Set of extensions for Autodesk Maya's Python API
Home-page: https://github.com/christophercrouzet/bana
Author: Christopher Crouzet
Author-email: christopher.crouzet@gmail.com
License: MIT
Keywords: Autodesk Maya API extension gorilla monkey patch
Platform: UNKNOWN
Classifier: Development Status :: 4 - Beta
Classifier: Intended Audience :: Developers
Classifier: License :: OSI Approved :: MIT License
Classifier: Programming Language :: Python
Classifier: Programming Language :: Python :: 2
Classifier: Programming Language :: Python :: 2.7
Classifier: Topic :: Software Development :: Libraries :: Python Modules
Classifier: Topic :: Utilities
Requires-Dist: gorilla (>=0.2.0)
Provides-Extra: dev
Requires-Dist: coverage; extra == 'dev'
Requires-Dist: revl; extra == 'dev'
Requires-Dist: sphinx (>=1.3); extra == 'dev'
Provides-Extra: docs
Requires-Dist: sphinx (>=1.3); extra == 'docs'
